Metadata-Version: 2.1
Name: espresso-caller
Version: 1.2.2
Summary: Automated and reproducible tool for identifying genomic variations at scale
Home-page: https://github.com/labbcb/espresso-caller
Author: Welliton de Souza, Benilton Carvalho
Author-email: well309@gmail.com, benilton@unicamp.br
License: MIT
Platform: UNKNOWN
Requires: click
Requires: requests
